optiguide/__init__.py
optiguide/optiguide.py
optiguide/version.py
OptiGuide-0.0.3.dist-info/LICENSE
OptiGuide-0.0.3.dist-info/METADATA
OptiGuide-0.0.3.dist-info/WHEEL
OptiGuide-0.0.3.dist-info/top_level.txt
OptiGuide-0.0.3.dist-info/RECORD
