Metadata-Version: 2.1
Name: OptiGuide
Version: 0.0.3
Summary: Large Language Models for Supply Chain Optimization
Home-page: https://github.com/microsoft/optiguide
Author: Beibin Li
Author-email: beibin.li@microsoft.com
Classifier: Programming Language :: Python :: 3
Classifier: License :: OSI Approved :: MIT License
Classifier: Operating System :: OS Independent
Requires-Python: >=3.8
License-File: LICENSE
Requires-Dist: openai (>=1.3)
Requires-Dist: diskcache
Requires-Dist: termcolor
Requires-Dist: pyautogen (>=0.2.0)
Requires-Dist: eventlet
Requires-Dist: gurobipy
Provides-Extra: test
Requires-Dist: pytest (>=6.1.1) ; extra == 'test'
Requires-Dist: pre-commit ; extra == 'test'
Requires-Dist: nbconvert ; extra == 'test'
Requires-Dist: nbformat ; extra == 'test'
Requires-Dist: ipykernel ; extra == 'test'
Requires-Dist: pydantic (==1.10.9) ; extra == 'test'
Requires-Dist: sympy ; extra == 'test'
